{
    "assignee": null,
    "assignees": [],
    "author_association": "MEMBER",
    "body": "",
    "closed_at": "2019-04-06T15:50:48Z",
    "comment_data": [
        {
            "author_association": "MEMBER",
            "body": "何不直接放到\"有活跃用户并且持续维护的开源项目\"一栏中?",
            "created_at": "2019-04-06T06:46:22Z",
            "html_url": "https://github.com/program-in-chinese/overview/pull/144#issuecomment-480479622",
            "id": 480479622,
            "issue_url": "https://api.github.com/repos/program-in-chinese/overview/issues/144",
            "node_id": "MDEyOklzc3VlQ29tbWVudDQ4MDQ3OTYyMg==",
            "updated_at": "2019-04-06T06:46:22Z",
            "url": "https://api.github.com/repos/program-in-chinese/overview/issues/comments/480479622",
            "user": {
                "avatar_url": "https://avatars1.githubusercontent.com/u/392497?v=4",
                "events_url": "https://api.github.com/users/nobodxbodon/events{/privacy}",
                "followers_url": "https://api.github.com/users/nobodxbodon/followers",
                "following_url": "https://api.github.com/users/nobodxbodon/following{/other_user}",
                "gists_url": "https://api.github.com/users/nobodxbodon/gists{/gist_id}",
                "gravatar_id": "",
                "html_url": "https://github.com/nobodxbodon",
                "id": 392497,
                "login": "nobodxbodon",
                "node_id": "MDQ6VXNlcjM5MjQ5Nw==",
                "organizations_url": "https://api.github.com/users/nobodxbodon/orgs",
                "received_events_url": "https://api.github.com/users/nobodxbodon/received_events",
                "repos_url": "https://api.github.com/users/nobodxbodon/repos",
                "site_admin": false,
                "starred_url": "https://api.github.com/users/nobodxbodon/starred{/owner}{/repo}",
                "subscriptions_url": "https://api.github.com/users/nobodxbodon/subscriptions",
                "type": "User",
                "url": "https://api.github.com/users/nobodxbodon"
            }
        },
        {
            "author_association": "MEMBER",
            "body": "\"黃油引擎\"有什么典故?  可否添加说明?",
            "created_at": "2019-04-06T07:38:31Z",
            "html_url": "https://github.com/program-in-chinese/overview/pull/144#issuecomment-480482887",
            "id": 480482887,
            "issue_url": "https://api.github.com/repos/program-in-chinese/overview/issues/144",
            "node_id": "MDEyOklzc3VlQ29tbWVudDQ4MDQ4Mjg4Nw==",
            "updated_at": "2019-04-06T07:38:31Z",
            "url": "https://api.github.com/repos/program-in-chinese/overview/issues/comments/480482887",
            "user": {
                "avatar_url": "https://avatars1.githubusercontent.com/u/392497?v=4",
                "events_url": "https://api.github.com/users/nobodxbodon/events{/privacy}",
                "followers_url": "https://api.github.com/users/nobodxbodon/followers",
                "following_url": "https://api.github.com/users/nobodxbodon/following{/other_user}",
                "gists_url": "https://api.github.com/users/nobodxbodon/gists{/gist_id}",
                "gravatar_id": "",
                "html_url": "https://github.com/nobodxbodon",
                "id": 392497,
                "login": "nobodxbodon",
                "node_id": "MDQ6VXNlcjM5MjQ5Nw==",
                "organizations_url": "https://api.github.com/users/nobodxbodon/orgs",
                "received_events_url": "https://api.github.com/users/nobodxbodon/received_events",
                "repos_url": "https://api.github.com/users/nobodxbodon/repos",
                "site_admin": false,
                "starred_url": "https://api.github.com/users/nobodxbodon/starred{/owner}{/repo}",
                "subscriptions_url": "https://api.github.com/users/nobodxbodon/subscriptions",
                "type": "User",
                "url": "https://api.github.com/users/nobodxbodon"
            }
        },
        {
            "author_association": "MEMBER",
            "body": "肥宅們習慣把galgame叫做黃油……和實際上黃不黃關係倒是不大。",
            "created_at": "2019-04-06T07:45:10Z",
            "html_url": "https://github.com/program-in-chinese/overview/pull/144#issuecomment-480483295",
            "id": 480483295,
            "issue_url": "https://api.github.com/repos/program-in-chinese/overview/issues/144",
            "node_id": "MDEyOklzc3VlQ29tbWVudDQ4MDQ4MzI5NQ==",
            "updated_at": "2019-04-06T07:45:10Z",
            "url": "https://api.github.com/repos/program-in-chinese/overview/issues/comments/480483295",
            "user": {
                "avatar_url": "https://avatars0.githubusercontent.com/u/20064807?v=4",
                "events_url": "https://api.github.com/users/RimoChan/events{/privacy}",
                "followers_url": "https://api.github.com/users/RimoChan/followers",
                "following_url": "https://api.github.com/users/RimoChan/following{/other_user}",
                "gists_url": "https://api.github.com/users/RimoChan/gists{/gist_id}",
                "gravatar_id": "",
                "html_url": "https://github.com/RimoChan",
                "id": 20064807,
                "login": "RimoChan",
                "node_id": "MDQ6VXNlcjIwMDY0ODA3",
                "organizations_url": "https://api.github.com/users/RimoChan/orgs",
                "received_events_url": "https://api.github.com/users/RimoChan/received_events",
                "repos_url": "https://api.github.com/users/RimoChan/repos",
                "site_admin": false,
                "starred_url": "https://api.github.com/users/RimoChan/starred{/owner}{/repo}",
                "subscriptions_url": "https://api.github.com/users/RimoChan/subscriptions",
                "type": "User",
                "url": "https://api.github.com/users/RimoChan"
            }
        },
        {
            "author_association": "MEMBER",
            "body": "哦, 原来如此. 👍",
            "created_at": "2019-04-06T15:50:43Z",
            "html_url": "https://github.com/program-in-chinese/overview/pull/144#issuecomment-480514639",
            "id": 480514639,
            "issue_url": "https://api.github.com/repos/program-in-chinese/overview/issues/144",
            "node_id": "MDEyOklzc3VlQ29tbWVudDQ4MDUxNDYzOQ==",
            "updated_at": "2019-04-06T15:50:43Z",
            "url": "https://api.github.com/repos/program-in-chinese/overview/issues/comments/480514639",
            "user": {
                "avatar_url": "https://avatars1.githubusercontent.com/u/392497?v=4",
                "events_url": "https://api.github.com/users/nobodxbodon/events{/privacy}",
                "followers_url": "https://api.github.com/users/nobodxbodon/followers",
                "following_url": "https://api.github.com/users/nobodxbodon/following{/other_user}",
                "gists_url": "https://api.github.com/users/nobodxbodon/gists{/gist_id}",
                "gravatar_id": "",
                "html_url": "https://github.com/nobodxbodon",
                "id": 392497,
                "login": "nobodxbodon",
                "node_id": "MDQ6VXNlcjM5MjQ5Nw==",
                "organizations_url": "https://api.github.com/users/nobodxbodon/orgs",
                "received_events_url": "https://api.github.com/users/nobodxbodon/received_events",
                "repos_url": "https://api.github.com/users/nobodxbodon/repos",
                "site_admin": false,
                "starred_url": "https://api.github.com/users/nobodxbodon/starred{/owner}{/repo}",
                "subscriptions_url": "https://api.github.com/users/nobodxbodon/subscriptions",
                "type": "User",
                "url": "https://api.github.com/users/nobodxbodon"
            }
        }
    ],
    "comments": 4,
    "comments_url": "https://api.github.com/repos/program-in-chinese/overview/issues/144/comments",
    "created_at": "2019-04-06T06:21:53Z",
    "event_data": [
        {
            "actor": {
                "avatar_url": "https://avatars1.githubusercontent.com/u/392497?v=4",
                "events_url": "https://api.github.com/users/nobodxbodon/events{/privacy}",
                "followers_url": "https://api.github.com/users/nobodxbodon/followers",
                "following_url": "https://api.github.com/users/nobodxbodon/following{/other_user}",
                "gists_url": "https://api.github.com/users/nobodxbodon/gists{/gist_id}",
                "gravatar_id": "",
                "html_url": "https://github.com/nobodxbodon",
                "id": 392497,
                "login": "nobodxbodon",
                "node_id": "MDQ6VXNlcjM5MjQ5Nw==",
                "organizations_url": "https://api.github.com/users/nobodxbodon/orgs",
                "received_events_url": "https://api.github.com/users/nobodxbodon/received_events",
                "repos_url": "https://api.github.com/users/nobodxbodon/repos",
                "site_admin": false,
                "starred_url": "https://api.github.com/users/nobodxbodon/starred{/owner}{/repo}",
                "subscriptions_url": "https://api.github.com/users/nobodxbodon/subscriptions",
                "type": "User",
                "url": "https://api.github.com/users/nobodxbodon"
            },
            "commit_id": "eebf53707bedad770779edea9959e5001d67acaa",
            "commit_url": "https://api.github.com/repos/program-in-chinese/overview/commits/eebf53707bedad770779edea9959e5001d67acaa",
            "created_at": "2019-04-06T15:50:48Z",
            "event": "referenced",
            "id": 2257507733,
            "node_id": "MDE1OlJlZmVyZW5jZWRFdmVudDIyNTc1MDc3MzM=",
            "url": "https://api.github.com/repos/program-in-chinese/overview/issues/events/2257507733"
        },
        {
            "actor": {
                "avatar_url": "https://avatars1.githubusercontent.com/u/392497?v=4",
                "events_url": "https://api.github.com/users/nobodxbodon/events{/privacy}",
                "followers_url": "https://api.github.com/users/nobodxbodon/followers",
                "following_url": "https://api.github.com/users/nobodxbodon/following{/other_user}",
                "gists_url": "https://api.github.com/users/nobodxbodon/gists{/gist_id}",
                "gravatar_id": "",
                "html_url": "https://github.com/nobodxbodon",
                "id": 392497,
                "login": "nobodxbodon",
                "node_id": "MDQ6VXNlcjM5MjQ5Nw==",
                "organizations_url": "https://api.github.com/users/nobodxbodon/orgs",
                "received_events_url": "https://api.github.com/users/nobodxbodon/received_events",
                "repos_url": "https://api.github.com/users/nobodxbodon/repos",
                "site_admin": false,
                "starred_url": "https://api.github.com/users/nobodxbodon/starred{/owner}{/repo}",
                "subscriptions_url": "https://api.github.com/users/nobodxbodon/subscriptions",
                "type": "User",
                "url": "https://api.github.com/users/nobodxbodon"
            },
            "commit_id": "eebf53707bedad770779edea9959e5001d67acaa",
            "commit_url": "https://api.github.com/repos/program-in-chinese/overview/commits/eebf53707bedad770779edea9959e5001d67acaa",
            "created_at": "2019-04-06T15:50:48Z",
            "event": "merged",
            "id": 2257507734,
            "node_id": "MDExOk1lcmdlZEV2ZW50MjI1NzUwNzczNA==",
            "url": "https://api.github.com/repos/program-in-chinese/overview/issues/events/2257507734"
        },
        {
            "actor": {
                "avatar_url": "https://avatars1.githubusercontent.com/u/392497?v=4",
                "events_url": "https://api.github.com/users/nobodxbodon/events{/privacy}",
                "followers_url": "https://api.github.com/users/nobodxbodon/followers",
                "following_url": "https://api.github.com/users/nobodxbodon/following{/other_user}",
                "gists_url": "https://api.github.com/users/nobodxbodon/gists{/gist_id}",
                "gravatar_id": "",
                "html_url": "https://github.com/nobodxbodon",
                "id": 392497,
                "login": "nobodxbodon",
                "node_id": "MDQ6VXNlcjM5MjQ5Nw==",
                "organizations_url": "https://api.github.com/users/nobodxbodon/orgs",
                "received_events_url": "https://api.github.com/users/nobodxbodon/received_events",
                "repos_url": "https://api.github.com/users/nobodxbodon/repos",
                "site_admin": false,
                "starred_url": "https://api.github.com/users/nobodxbodon/starred{/owner}{/repo}",
                "subscriptions_url": "https://api.github.com/users/nobodxbodon/subscriptions",
                "type": "User",
                "url": "https://api.github.com/users/nobodxbodon"
            },
            "commit_id": null,
            "commit_url": null,
            "created_at": "2019-04-06T15:50:48Z",
            "event": "closed",
            "id": 2257507735,
            "node_id": "MDExOkNsb3NlZEV2ZW50MjI1NzUwNzczNQ==",
            "url": "https://api.github.com/repos/program-in-chinese/overview/issues/events/2257507735"
        }
    ],
    "events_url": "https://api.github.com/repos/program-in-chinese/overview/issues/144/events",
    "html_url": "https://github.com/program-in-chinese/overview/pull/144",
    "id": 430002896,
    "labels": [],
    "labels_url": "https://api.github.com/repos/program-in-chinese/overview/issues/144/labels{/name}",
    "locked": false,
    "milestone": null,
    "node_id": "MDExOlB1bGxSZXF1ZXN0MjY4MDE2MzI2",
    "number": 144,
    "pull_request": {
        "diff_url": "https://github.com/program-in-chinese/overview/pull/144.diff",
        "html_url": "https://github.com/program-in-chinese/overview/pull/144",
        "patch_url": "https://github.com/program-in-chinese/overview/pull/144.patch",
        "url": "https://api.github.com/repos/program-in-chinese/overview/pulls/144"
    },
    "repository_url": "https://api.github.com/repos/program-in-chinese/overview",
    "state": "closed",
    "title": "添加RimoChan的Librian項目。",
    "updated_at": "2019-04-06T15:50:48Z",
    "url": "https://api.github.com/repos/program-in-chinese/overview/issues/144",
    "user": {
        "avatar_url": "https://avatars0.githubusercontent.com/u/20064807?v=4",
        "events_url": "https://api.github.com/users/RimoChan/events{/privacy}",
        "followers_url": "https://api.github.com/users/RimoChan/followers",
        "following_url": "https://api.github.com/users/RimoChan/following{/other_user}",
        "gists_url": "https://api.github.com/users/RimoChan/gists{/gist_id}",
        "gravatar_id": "",
        "html_url": "https://github.com/RimoChan",
        "id": 20064807,
        "login": "RimoChan",
        "node_id": "MDQ6VXNlcjIwMDY0ODA3",
        "organizations_url": "https://api.github.com/users/RimoChan/orgs",
        "received_events_url": "https://api.github.com/users/RimoChan/received_events",
        "repos_url": "https://api.github.com/users/RimoChan/repos",
        "site_admin": false,
        "starred_url": "https://api.github.com/users/RimoChan/starred{/owner}{/repo}",
        "subscriptions_url": "https://api.github.com/users/RimoChan/subscriptions",
        "type": "User",
        "url": "https://api.github.com/users/RimoChan"
    }
}