{
    "assignee": null,
    "assignees": [],
    "author_association": "MEMBER",
    "body": "",
    "closed_at": "2019-05-07T02:35:47Z",
    "comment_data": [
        {
            "author_association": "MEMBER",
            "body": "多谢。可否在开头加上注释，说明在哪个环境（编译器）运行通过？",
            "created_at": "2019-05-07T02:25:39Z",
            "html_url": "https://github.com/program-in-chinese/overview/pull/151#issuecomment-489882187",
            "id": 489882187,
            "issue_url": "https://api.github.com/repos/program-in-chinese/overview/issues/151",
            "node_id": "MDEyOklzc3VlQ29tbWVudDQ4OTg4MjE4Nw==",
            "updated_at": "2019-05-07T02:25:39Z",
            "url": "https://api.github.com/repos/program-in-chinese/overview/issues/comments/489882187",
            "user": {
                "avatar_url": "https://avatars1.githubusercontent.com/u/392497?v=4",
                "events_url": "https://api.github.com/users/nobodxbodon/events{/privacy}",
                "followers_url": "https://api.github.com/users/nobodxbodon/followers",
                "following_url": "https://api.github.com/users/nobodxbodon/following{/other_user}",
                "gists_url": "https://api.github.com/users/nobodxbodon/gists{/gist_id}",
                "gravatar_id": "",
                "html_url": "https://github.com/nobodxbodon",
                "id": 392497,
                "login": "nobodxbodon",
                "node_id": "MDQ6VXNlcjM5MjQ5Nw==",
                "organizations_url": "https://api.github.com/users/nobodxbodon/orgs",
                "received_events_url": "https://api.github.com/users/nobodxbodon/received_events",
                "repos_url": "https://api.github.com/users/nobodxbodon/repos",
                "site_admin": false,
                "starred_url": "https://api.github.com/users/nobodxbodon/starred{/owner}{/repo}",
                "subscriptions_url": "https://api.github.com/users/nobodxbodon/subscriptions",
                "type": "User",
                "url": "https://api.github.com/users/nobodxbodon"
            }
        },
        {
            "author_association": "MEMBER",
            "body": "比如 https://github.com/program-in-chinese/overview/blob/master/%E7%A4%BA%E4%BE%8B%E4%BB%A3%E7%A0%81/%E6%96%90%E6%B3%A2%E9%82%A3%E5%A5%91.pl",
            "created_at": "2019-05-07T02:26:02Z",
            "html_url": "https://github.com/program-in-chinese/overview/pull/151#issuecomment-489882263",
            "id": 489882263,
            "issue_url": "https://api.github.com/repos/program-in-chinese/overview/issues/151",
            "node_id": "MDEyOklzc3VlQ29tbWVudDQ4OTg4MjI2Mw==",
            "updated_at": "2019-05-07T02:26:02Z",
            "url": "https://api.github.com/repos/program-in-chinese/overview/issues/comments/489882263",
            "user": {
                "avatar_url": "https://avatars1.githubusercontent.com/u/392497?v=4",
                "events_url": "https://api.github.com/users/nobodxbodon/events{/privacy}",
                "followers_url": "https://api.github.com/users/nobodxbodon/followers",
                "following_url": "https://api.github.com/users/nobodxbodon/following{/other_user}",
                "gists_url": "https://api.github.com/users/nobodxbodon/gists{/gist_id}",
                "gravatar_id": "",
                "html_url": "https://github.com/nobodxbodon",
                "id": 392497,
                "login": "nobodxbodon",
                "node_id": "MDQ6VXNlcjM5MjQ5Nw==",
                "organizations_url": "https://api.github.com/users/nobodxbodon/orgs",
                "received_events_url": "https://api.github.com/users/nobodxbodon/received_events",
                "repos_url": "https://api.github.com/users/nobodxbodon/repos",
                "site_admin": false,
                "starred_url": "https://api.github.com/users/nobodxbodon/starred{/owner}{/repo}",
                "subscriptions_url": "https://api.github.com/users/nobodxbodon/subscriptions",
                "type": "User",
                "url": "https://api.github.com/users/nobodxbodon"
            }
        },
        {
            "author_association": "MEMBER",
            "body": "增加了。",
            "created_at": "2019-05-07T02:33:58Z",
            "html_url": "https://github.com/program-in-chinese/overview/pull/151#issuecomment-489883755",
            "id": 489883755,
            "issue_url": "https://api.github.com/repos/program-in-chinese/overview/issues/151",
            "node_id": "MDEyOklzc3VlQ29tbWVudDQ4OTg4Mzc1NQ==",
            "updated_at": "2019-05-07T02:33:58Z",
            "url": "https://api.github.com/repos/program-in-chinese/overview/issues/comments/489883755",
            "user": {
                "avatar_url": "https://avatars2.githubusercontent.com/u/19170231?v=4",
                "events_url": "https://api.github.com/users/zaoqi/events{/privacy}",
                "followers_url": "https://api.github.com/users/zaoqi/followers",
                "following_url": "https://api.github.com/users/zaoqi/following{/other_user}",
                "gists_url": "https://api.github.com/users/zaoqi/gists{/gist_id}",
                "gravatar_id": "",
                "html_url": "https://github.com/zaoqi",
                "id": 19170231,
                "login": "zaoqi",
                "node_id": "MDQ6VXNlcjE5MTcwMjMx",
                "organizations_url": "https://api.github.com/users/zaoqi/orgs",
                "received_events_url": "https://api.github.com/users/zaoqi/received_events",
                "repos_url": "https://api.github.com/users/zaoqi/repos",
                "site_admin": false,
                "starred_url": "https://api.github.com/users/zaoqi/starred{/owner}{/repo}",
                "subscriptions_url": "https://api.github.com/users/zaoqi/subscriptions",
                "type": "User",
                "url": "https://api.github.com/users/zaoqi"
            }
        },
        {
            "author_association": "MEMBER",
            "body": "赞！",
            "created_at": "2019-05-07T02:35:30Z",
            "html_url": "https://github.com/program-in-chinese/overview/pull/151#issuecomment-489884048",
            "id": 489884048,
            "issue_url": "https://api.github.com/repos/program-in-chinese/overview/issues/151",
            "node_id": "MDEyOklzc3VlQ29tbWVudDQ4OTg4NDA0OA==",
            "updated_at": "2019-05-07T02:35:30Z",
            "url": "https://api.github.com/repos/program-in-chinese/overview/issues/comments/489884048",
            "user": {
                "avatar_url": "https://avatars1.githubusercontent.com/u/392497?v=4",
                "events_url": "https://api.github.com/users/nobodxbodon/events{/privacy}",
                "followers_url": "https://api.github.com/users/nobodxbodon/followers",
                "following_url": "https://api.github.com/users/nobodxbodon/following{/other_user}",
                "gists_url": "https://api.github.com/users/nobodxbodon/gists{/gist_id}",
                "gravatar_id": "",
                "html_url": "https://github.com/nobodxbodon",
                "id": 392497,
                "login": "nobodxbodon",
                "node_id": "MDQ6VXNlcjM5MjQ5Nw==",
                "organizations_url": "https://api.github.com/users/nobodxbodon/orgs",
                "received_events_url": "https://api.github.com/users/nobodxbodon/received_events",
                "repos_url": "https://api.github.com/users/nobodxbodon/repos",
                "site_admin": false,
                "starred_url": "https://api.github.com/users/nobodxbodon/starred{/owner}{/repo}",
                "subscriptions_url": "https://api.github.com/users/nobodxbodon/subscriptions",
                "type": "User",
                "url": "https://api.github.com/users/nobodxbodon"
            }
        }
    ],
    "comments": 4,
    "comments_url": "https://api.github.com/repos/program-in-chinese/overview/issues/151/comments",
    "created_at": "2019-05-07T01:50:03Z",
    "event_data": [
        {
            "actor": {
                "avatar_url": "https://avatars2.githubusercontent.com/u/19170231?v=4",
                "events_url": "https://api.github.com/users/zaoqi/events{/privacy}",
                "followers_url": "https://api.github.com/users/zaoqi/followers",
                "following_url": "https://api.github.com/users/zaoqi/following{/other_user}",
                "gists_url": "https://api.github.com/users/zaoqi/gists{/gist_id}",
                "gravatar_id": "",
                "html_url": "https://github.com/zaoqi",
                "id": 19170231,
                "login": "zaoqi",
                "node_id": "MDQ6VXNlcjE5MTcwMjMx",
                "organizations_url": "https://api.github.com/users/zaoqi/orgs",
                "received_events_url": "https://api.github.com/users/zaoqi/received_events",
                "repos_url": "https://api.github.com/users/zaoqi/repos",
                "site_admin": false,
                "starred_url": "https://api.github.com/users/zaoqi/starred{/owner}{/repo}",
                "subscriptions_url": "https://api.github.com/users/zaoqi/subscriptions",
                "type": "User",
                "url": "https://api.github.com/users/zaoqi"
            },
            "commit_id": "5f011936ef555ce84ab647806981045c47964f84",
            "commit_url": "https://api.github.com/repos/zaoqi-clone/team_website/commits/5f011936ef555ce84ab647806981045c47964f84",
            "created_at": "2019-05-07T02:12:09Z",
            "event": "referenced",
            "id": 2322752532,
            "node_id": "MDE1OlJlZmVyZW5jZWRFdmVudDIzMjI3NTI1MzI=",
            "url": "https://api.github.com/repos/program-in-chinese/overview/issues/events/2322752532"
        },
        {
            "actor": {
                "avatar_url": "https://avatars1.githubusercontent.com/u/392497?v=4",
                "events_url": "https://api.github.com/users/nobodxbodon/events{/privacy}",
                "followers_url": "https://api.github.com/users/nobodxbodon/followers",
                "following_url": "https://api.github.com/users/nobodxbodon/following{/other_user}",
                "gists_url": "https://api.github.com/users/nobodxbodon/gists{/gist_id}",
                "gravatar_id": "",
                "html_url": "https://github.com/nobodxbodon",
                "id": 392497,
                "login": "nobodxbodon",
                "node_id": "MDQ6VXNlcjM5MjQ5Nw==",
                "organizations_url": "https://api.github.com/users/nobodxbodon/orgs",
                "received_events_url": "https://api.github.com/users/nobodxbodon/received_events",
                "repos_url": "https://api.github.com/users/nobodxbodon/repos",
                "site_admin": false,
                "starred_url": "https://api.github.com/users/nobodxbodon/starred{/owner}{/repo}",
                "subscriptions_url": "https://api.github.com/users/nobodxbodon/subscriptions",
                "type": "User",
                "url": "https://api.github.com/users/nobodxbodon"
            },
            "commit_id": "7121fb8bd3b043fc93f4f8c0f9029aeac3cd60fe",
            "commit_url": "https://api.github.com/repos/program-in-chinese/overview/commits/7121fb8bd3b043fc93f4f8c0f9029aeac3cd60fe",
            "created_at": "2019-05-07T02:35:47Z",
            "event": "referenced",
            "id": 2322782487,
            "node_id": "MDE1OlJlZmVyZW5jZWRFdmVudDIzMjI3ODI0ODc=",
            "url": "https://api.github.com/repos/program-in-chinese/overview/issues/events/2322782487"
        },
        {
            "actor": {
                "avatar_url": "https://avatars1.githubusercontent.com/u/392497?v=4",
                "events_url": "https://api.github.com/users/nobodxbodon/events{/privacy}",
                "followers_url": "https://api.github.com/users/nobodxbodon/followers",
                "following_url": "https://api.github.com/users/nobodxbodon/following{/other_user}",
                "gists_url": "https://api.github.com/users/nobodxbodon/gists{/gist_id}",
                "gravatar_id": "",
                "html_url": "https://github.com/nobodxbodon",
                "id": 392497,
                "login": "nobodxbodon",
                "node_id": "MDQ6VXNlcjM5MjQ5Nw==",
                "organizations_url": "https://api.github.com/users/nobodxbodon/orgs",
                "received_events_url": "https://api.github.com/users/nobodxbodon/received_events",
                "repos_url": "https://api.github.com/users/nobodxbodon/repos",
                "site_admin": false,
                "starred_url": "https://api.github.com/users/nobodxbodon/starred{/owner}{/repo}",
                "subscriptions_url": "https://api.github.com/users/nobodxbodon/subscriptions",
                "type": "User",
                "url": "https://api.github.com/users/nobodxbodon"
            },
            "commit_id": "7121fb8bd3b043fc93f4f8c0f9029aeac3cd60fe",
            "commit_url": "https://api.github.com/repos/program-in-chinese/overview/commits/7121fb8bd3b043fc93f4f8c0f9029aeac3cd60fe",
            "created_at": "2019-05-07T02:35:47Z",
            "event": "merged",
            "id": 2322782489,
            "node_id": "MDExOk1lcmdlZEV2ZW50MjMyMjc4MjQ4OQ==",
            "url": "https://api.github.com/repos/program-in-chinese/overview/issues/events/2322782489"
        },
        {
            "actor": {
                "avatar_url": "https://avatars1.githubusercontent.com/u/392497?v=4",
                "events_url": "https://api.github.com/users/nobodxbodon/events{/privacy}",
                "followers_url": "https://api.github.com/users/nobodxbodon/followers",
                "following_url": "https://api.github.com/users/nobodxbodon/following{/other_user}",
                "gists_url": "https://api.github.com/users/nobodxbodon/gists{/gist_id}",
                "gravatar_id": "",
                "html_url": "https://github.com/nobodxbodon",
                "id": 392497,
                "login": "nobodxbodon",
                "node_id": "MDQ6VXNlcjM5MjQ5Nw==",
                "organizations_url": "https://api.github.com/users/nobodxbodon/orgs",
                "received_events_url": "https://api.github.com/users/nobodxbodon/received_events",
                "repos_url": "https://api.github.com/users/nobodxbodon/repos",
                "site_admin": false,
                "starred_url": "https://api.github.com/users/nobodxbodon/starred{/owner}{/repo}",
                "subscriptions_url": "https://api.github.com/users/nobodxbodon/subscriptions",
                "type": "User",
                "url": "https://api.github.com/users/nobodxbodon"
            },
            "commit_id": null,
            "commit_url": null,
            "created_at": "2019-05-07T02:35:47Z",
            "event": "closed",
            "id": 2322782491,
            "node_id": "MDExOkNsb3NlZEV2ZW50MjMyMjc4MjQ5MQ==",
            "url": "https://api.github.com/repos/program-in-chinese/overview/issues/events/2322782491"
        }
    ],
    "events_url": "https://api.github.com/repos/program-in-chinese/overview/issues/151/events",
    "html_url": "https://github.com/program-in-chinese/overview/pull/151",
    "id": 440988231,
    "labels": [],
    "labels_url": "https://api.github.com/repos/program-in-chinese/overview/issues/151/labels{/name}",
    "locked": false,
    "milestone": null,
    "node_id": "MDExOlB1bGxSZXF1ZXN0Mjc2NDEyMTg5",
    "number": 151,
    "pull_request": {
        "diff_url": "https://github.com/program-in-chinese/overview/pull/151.diff",
        "html_url": "https://github.com/program-in-chinese/overview/pull/151",
        "patch_url": "https://github.com/program-in-chinese/overview/pull/151.patch",
        "url": "https://api.github.com/repos/program-in-chinese/overview/pulls/151"
    },
    "repository_url": "https://api.github.com/repos/program-in-chinese/overview",
    "state": "closed",
    "title": "Create Racket示例.rkt",
    "updated_at": "2019-05-07T02:35:47Z",
    "url": "https://api.github.com/repos/program-in-chinese/overview/issues/151",
    "user": {
        "avatar_url": "https://avatars2.githubusercontent.com/u/19170231?v=4",
        "events_url": "https://api.github.com/users/zaoqi/events{/privacy}",
        "followers_url": "https://api.github.com/users/zaoqi/followers",
        "following_url": "https://api.github.com/users/zaoqi/following{/other_user}",
        "gists_url": "https://api.github.com/users/zaoqi/gists{/gist_id}",
        "gravatar_id": "",
        "html_url": "https://github.com/zaoqi",
        "id": 19170231,
        "login": "zaoqi",
        "node_id": "MDQ6VXNlcjE5MTcwMjMx",
        "organizations_url": "https://api.github.com/users/zaoqi/orgs",
        "received_events_url": "https://api.github.com/users/zaoqi/received_events",
        "repos_url": "https://api.github.com/users/zaoqi/repos",
        "site_admin": false,
        "starred_url": "https://api.github.com/users/zaoqi/starred{/owner}{/repo}",
        "subscriptions_url": "https://api.github.com/users/zaoqi/subscriptions",
        "type": "User",
        "url": "https://api.github.com/users/zaoqi"
    }
}